yumma/__init__.py
yumma/main.py
yumma-1.4.8.8.dist-info/METADATA
yumma-1.4.8.8.dist-info/WHEEL
yumma-1.4.8.8.dist-info/top_level.txt
yumma-1.4.8.8.dist-info/RECORD
