Metadata-Version: 2.1
Name: yumma
Version: 1.4.8.8
Summary: Test version of the yumma package
Author-email: geniyibani <jsjsjdidjssjdj@gmail.com>
License: MIT
Project-URL: Documentation, https://t.me/moduleslist
Project-URL: Source, https://github.com/your-repo
Classifier: Programming Language :: Python :: 3
Classifier: License :: OSI Approved :: MIT License
Classifier: Operating System :: OS Independent
Requires-Python: >=3.6
Requires-Dist: Telethon
